velogames/__init__.py
velogames/cli.py
velogames/commands.py
velogames/containers.py
velogames/parser.py
velogames-0.1.1.dist-info/entry_points.txt
velogames-0.1.1.dist-info/WHEEL
velogames-0.1.1.dist-info/METADATA
velogames-0.1.1.dist-info/RECORD
